nrpc/__init__.py
nrpc/exc.py
nrpc/gen.py
nrpc/lib.py
nrpc/nrpc.proto
nrpc/nrpc_pb2.py
nrpc/nrpc_pb2.pyi
nrpc/tmpl.mako
nrpc/tmpl.py
python_nrpc-0.0.8.dist-info/licenses/LICENSE
python_nrpc-0.0.8.dist-info/METADATA
python_nrpc-0.0.8.dist-info/WHEEL
python_nrpc-0.0.8.dist-info/entry_points.txt
python_nrpc-0.0.8.dist-info/top_level.txt
python_nrpc-0.0.8.dist-info/RECORD
