Metadata-Version: 2.4
Name: python-nrpc
Version: 0.0.8
Summary: A python code generator and lib for Nats RPC
Author-email: Christophe de Vienne <christophe.devienne@orbeet.io>
License-Expression: MIT
Project-URL: Homepage, https://github.com/nats-rpc/python-nrpc
Project-URL: Issues, https://github.com/nats-rpc/python-nrpc/issues
Classifier: Programming Language :: Python :: 3
Classifier: Operating System :: OS Independent
Requires-Python: >=3.9
License-File: LICENSE
Requires-Dist: protobuf
Requires-Dist: mako
Requires-Dist: nats-py>=2.7
Dynamic: license-file
